{
  "characters": [
    {
      "name": "Bibi",
      "from": 0,
      "durationInFrames": 390,
      "artists": [
        {
          "name": "m5memiou",
          "durationInFrames": 360,
          "from": 30,
          "network": null,
          "artworks": [
            {
              "url": "slideshow/4edb8daf-c04c-4fc4-943c-23f875c0028b..png",
              "durationInFrames": 90,
              "from": 0
            },
            {
              "url": "slideshow/a2d2fe68-faa7-4cc0-8047-166d0094bd9a..png",
              "durationInFrames": 90,
              "from": 90
            },
            {
              "url": "slideshow/49da23ce-4d80-4e91-a2e4-6561d5c6ec36..png",
              "durationInFrames": 90,
              "from": 180
            },
            {
              "url": "slideshow/d4261129-1160-4cdd-866a-65c0d14dbf6a..png",
              "durationInFrames": 90,
              "from": 270
            }
          ]
        }
      ]
    },
    {
      "name": "Meco",
      "from": 390,
      "durationInFrames": 120,
      "artists": [
        {
          "name": "Sadcatz",
          "durationInFrames": 90,
          "from": 30,
          "network": "FA: sadcat16hrz",
          "artworks": [
            {
              "url": "slideshow/3e911734-581b-496d-af80-ffb809213186..png",
              "durationInFrames": 90,
              "from": 0
            }
          ]
        }
      ]
    }
  ],
  "fps": 30,
  "from": 0,
  "durationInFrames": 630,
  "introDurationInFrames": 120
}